sumadora/__init__.py
sumadora/__main__.py
sumadora/__version__.py
sumadora/sumadora.py
sumadora-0.0.13.dist-info/entry_points.txt
sumadora-0.0.13.dist-info/WHEEL
sumadora-0.0.13.dist-info/METADATA
sumadora-0.0.13.dist-info/RECORD
