Metadata-Version: 2.1
Name: sumadora
Version: 0.0.13
Summary: Sumador básico
Home-page: https://github.com/lsantiago/DemoPackage
License: MIT
Keywords: calculadora,sumadora
Author: Santiago Quiñones
Requires-Python: >=3.8,<4.0
Classifier: License :: OSI Approved :: MIT License
Classifier: Programming Language :: Python :: 3
Classifier: Programming Language :: Python :: 3.8
Classifier: Programming Language :: Python :: 3.9
Requires-Dist: click (>=8.0.1,<9.0.0)
Project-URL: Repository, https://github.com/lsantiago/DemoPackage
